weave/weaveapi/auth/v1/service_pb2.py
weave/weaveapi/auth/v1/service_pb2.pyi
weave/weaveapi/auth/v1/service_pb2_grpc.py
weave/weaveapi/auth/v1/service_pb2_grpc.pyi
weave/weaveapi/auth/v1/session_pb2.py
weave/weaveapi/auth/v1/session_pb2.pyi
weave/weaveapi/auth/v1/session_pb2_grpc.py
weave/weaveapi/auth/v1/session_pb2_grpc.pyi
weave/weaveapi/auth/v1/usage_pb2.py
weave/weaveapi/auth/v1/usage_pb2.pyi
weave/weaveapi/auth/v1/usage_pb2_grpc.py
weave/weaveapi/auth/v1/usage_pb2_grpc.pyi
weave/weaveapi/auth/v1/user_pb2.py
weave/weaveapi/auth/v1/user_pb2.pyi
weave/weaveapi/auth/v1/user_pb2_grpc.py
weave/weaveapi/auth/v1/user_pb2_grpc.pyi
weave/weaveapi/generate/v1/configuration_pb2.py
weave/weaveapi/generate/v1/configuration_pb2.pyi
weave/weaveapi/generate/v1/configuration_pb2_grpc.py
weave/weaveapi/generate/v1/configuration_pb2_grpc.pyi
weave/weaveapi/generate/v1/generate_pb2.py
weave/weaveapi/generate/v1/generate_pb2.pyi
weave/weaveapi/generate/v1/generate_pb2_grpc.py
weave/weaveapi/generate/v1/generate_pb2_grpc.pyi
weave/weaveapi/generate/v1/service_pb2.py
weave/weaveapi/generate/v1/service_pb2.pyi
weave/weaveapi/generate/v1/service_pb2_grpc.py
weave/weaveapi/generate/v1/service_pb2_grpc.pyi
weave/weaveapi/llmx/v1/architecture_pb2.py
weave/weaveapi/llmx/v1/architecture_pb2.pyi
weave/weaveapi/llmx/v1/architecture_pb2_grpc.py
weave/weaveapi/llmx/v1/architecture_pb2_grpc.pyi
weave/weaveapi/llmx/v1/capabilities_pb2.py
weave/weaveapi/llmx/v1/capabilities_pb2.pyi
weave/weaveapi/llmx/v1/capabilities_pb2_grpc.py
weave/weaveapi/llmx/v1/capabilities_pb2_grpc.pyi
weave/weaveapi/llmx/v1/model_pb2.py
weave/weaveapi/llmx/v1/model_pb2.pyi
weave/weaveapi/llmx/v1/model_pb2_grpc.py
weave/weaveapi/llmx/v1/model_pb2_grpc.pyi
weave/weaveapi/llmx/v1/pricing_pb2.py
weave/weaveapi/llmx/v1/pricing_pb2.pyi
weave/weaveapi/llmx/v1/pricing_pb2_grpc.py
weave/weaveapi/llmx/v1/pricing_pb2_grpc.pyi
weave/weaveapi/llmx/v1/provider_pb2.py
weave/weaveapi/llmx/v1/provider_pb2.pyi
weave_python-0.28.1.dist-info/METADATA
weave_python-0.28.1.dist-info/WHEEL
weave_python-0.28.1.dist-info/RECORD
