Metadata-Version: 2.4
Name: weave-python
Version: 0.28.1
Requires-Python: >=3.10
Requires-Dist: protobuf>=6.30.2
Requires-Dist: sqlalchemy>=2.0.40
